smurfs/__init__.py
smurfs/__main__.py
smurfs/preprocessing/__init__.py
smurfs/preprocessing/calculators.py
smurfs/preprocessing/dataloader.py
smurfs/signal/__init__.py
smurfs/signal/frequency_finder.py
smurfs/signal/lightcurve.py
smurfs/signal/periodogram.py
smurfs/smurfs_/__init__.py
smurfs/smurfs_/smurfs.py
smurfs/support/__init__.py
smurfs/support/cd.py
smurfs/support/mprint.py
smurfs/support/settings.py
smurfs-2.0.0.dist-info/LICENSE
smurfs-2.0.0.dist-info/METADATA
smurfs-2.0.0.dist-info/WHEEL
smurfs-2.0.0.dist-info/RECORD
