Metadata-Version: 2.1
Name: smurfs
Version: 2.0.0
Summary: Smart UseR Frequency analySer
License: MIT
Author: Marco Muellner
Author-email: muellnermarco@gmail.com
Requires-Python: >=3.10,<4.0
Classifier: License :: OSI Approved :: MIT License
Classifier: Programming Language :: Python :: 3
Classifier: Programming Language :: Python :: 3.10
Classifier: Programming Language :: Python :: 3.11
Classifier: Programming Language :: Python :: 3.12
Requires-Dist: astropy (>=6.1.4,<7.0.0)
Requires-Dist: astroquery (>=0.4.7,<0.5.0)
Requires-Dist: eleanor (>=2.0.5,<3.0.0)
Requires-Dist: jupyter (>=1.1.1,<2.0.0)
Requires-Dist: lightkurve (>=2.5.0,<3.0.0)
Requires-Dist: lmfit (>=1.3.2,<2.0.0)
Requires-Dist: matplotlib (>=3.9.2,<4.0.0)
Requires-Dist: nbsphinx (>=0.9.5,<0.10.0)
Requires-Dist: numpy (>=2.1.1,<3.0.0)
Requires-Dist: pandas (>=2.2.3,<3.0.0)
Requires-Dist: pyfcomb (>=2.1.0,<3.0.0)
Requires-Dist: scipy (>=1.14.1,<2.0.0)
Requires-Dist: typer (>=0.12.5,<0.13.0)
Requires-Dist: uncertainties (>=3.2.2,<4.0.0)
